honorific/__init__.py
honorific/honorific.py
honorific-0.1.5.dist-info/METADATA
honorific-0.1.5.dist-info/WHEEL
honorific-0.1.5.dist-info/RECORD
