Metadata-Version: 2.1
Name: honorific
Version: 0.1.5
Summary: Изменение числа во втором лице
Home-page: https://git.promo-bot.ru/v.merkurev/honorific
Keywords: promo-bot,promobot
Author: Viktor Merkurev
Author-email: v.merkurev@promo-bot.ru
Maintainer: VMerkurev
Maintainer-email: v.merkurev@promo-bot.ru
Requires-Python: >=3.8,<4.0
Classifier: Programming Language :: Python :: 3
Classifier: Programming Language :: Python :: 3.8
Classifier: Programming Language :: Python :: 3.9
Classifier: Programming Language :: Python :: 3.10
Classifier: Programming Language :: Python :: 3.11
Requires-Dist: pymorphy2 (>=0.9.1,<0.10.0)
Requires-Dist: spacy (>=3.4.3,<4.0.0)
Requires-Dist: twine (>=4.0.2,<5.0.0)
Project-URL: Repository, https://git.promo-bot.ru/v.merkurev/honorific
